api2pdf/__init__.py
api2pdf/api2pdf.py
api2pdf-2.1.0.dist-info/LICENSE.txt
api2pdf-2.1.0.dist-info/METADATA
api2pdf-2.1.0.dist-info/WHEEL
api2pdf-2.1.0.dist-info/top_level.txt
api2pdf-2.1.0.dist-info/RECORD
