Metadata-Version: 2.1
Name: api2pdf
Version: 2.1.0
Summary: This client library is a wrapper for the Api2Pdf.com REST API. See full REST api documentation at https://www.api2pdf.com/documentation/v2. Api2Pdf is a powerful API that supports HTML to PDF, URL to PDF, HTML to Image, URL to Image, Thumbnail / image preview of an Office file, Office files (Word to PDF), HTML to Docx, HTML to excel, PDF to HTML, merge PDFs together, add bookmarks to PDFs, add passwords to PDFs
Home-page: https://github.com/api2pdf/api2pdf.python
Author: Zack Schwartz
Author-email: support@api2pdf.com
License: UNKNOWN
Platform: UNKNOWN
Classifier: Programming Language :: Python :: 3
Classifier: License :: OSI Approved :: MIT License
Classifier: Operating System :: OS Independent
Requires-Dist: requests
